<?xml version="1.0" encoding="utf-8"?>
<EntityRelationships>
  <EntityRelationship Name="msdyn_bookableresourcecategory_bookableresourcebooking_resourcecategoryid">
    <EntityRelationshipType>OneToMany</EntityRelationshipType>
    <IntroducedVersion>1.0.1.1</IntroducedVersion>
    <IsHierarchical>0</IsHierarchical>
    <ReferencingEntityName>BookableResourceBooking</ReferencingEntityName>
    <ReferencedEntityName>BookableResourceCategory</ReferencedEntityName>
    <CascadeAssign>NoCascade</CascadeAssign>
    <CascadeDelete>RemoveLink</CascadeDelete>
    <CascadeReparent>NoCascade</CascadeReparent>
    <CascadeShare>NoCascade</CascadeShare>
    <CascadeUnshare>NoCascade</CascadeUnshare>
    <CascadeRollupView>NoCascade</CascadeRollupView>
    <IsValidForAdvancedFind>1</IsValidForAdvancedFind>
    <ReferencingAttributeName>msdyn_resourcecategoryid</ReferencingAttributeName>
    <RelationshipDescription>
      <Descriptions>
        <Description description="Resource Category" languagecode="1033" />
      </Descriptions>
    </RelationshipDescription>
    <EntityRelationshipRoles>
      <EntityRelationshipRole>
        <NavPaneDisplayOption>UseCollectionName</NavPaneDisplayOption>
        <NavPaneArea>Details</NavPaneArea>
        <NavPaneOrder>10000</NavPaneOrder>
        <NavigationPropertyName>msdyn_resourcecategoryid</NavigationPropertyName>
        <CustomLabels>
          <CustomLabel description="" languagecode="1033" />
        </CustomLabels>
        <RelationshipRoleType>1</RelationshipRoleType>
      </EntityRelationshipRole>
      <EntityRelationshipRole>
        <RelationshipRoleType>0</RelationshipRoleType>
      </EntityRelationshipRole>
    </EntityRelationshipRoles>
  </EntityRelationship>
  <EntityRelationship Name="msdyn_bookableresourcecategory_bookableresourcebookingheader_resourcecategoryid">
    <EntityRelationshipType>OneToMany</EntityRelationshipType>
    <IntroducedVersion>1.0.1.1</IntroducedVersion>
    <IsHierarchical>0</IsHierarchical>
    <ReferencingEntityName>BookableResourceBookingHeader</ReferencingEntityName>
    <ReferencedEntityName>BookableResourceCategory</ReferencedEntityName>
    <CascadeAssign>NoCascade</CascadeAssign>
    <CascadeDelete>RemoveLink</CascadeDelete>
    <CascadeReparent>NoCascade</CascadeReparent>
    <CascadeShare>NoCascade</CascadeShare>
    <CascadeUnshare>NoCascade</CascadeUnshare>
    <CascadeRollupView>NoCascade</CascadeRollupView>
    <IsValidForAdvancedFind>1</IsValidForAdvancedFind>
    <ReferencingAttributeName>msdyn_resourcecategoryid</ReferencingAttributeName>
    <RelationshipDescription>
      <Descriptions>
        <Description description="Resource Category" languagecode="1033" />
      </Descriptions>
    </RelationshipDescription>
    <EntityRelationshipRoles>
      <EntityRelationshipRole>
        <NavPaneDisplayOption>UseCollectionName</NavPaneDisplayOption>
        <NavPaneArea>Details</NavPaneArea>
        <NavPaneOrder>10000</NavPaneOrder>
        <NavigationPropertyName>msdyn_resourcecategoryid</NavigationPropertyName>
        <CustomLabels>
          <CustomLabel description="" languagecode="1033" />
        </CustomLabels>
        <RelationshipRoleType>1</RelationshipRoleType>
      </EntityRelationshipRole>
      <EntityRelationshipRole>
        <RelationshipRoleType>0</RelationshipRoleType>
      </EntityRelationshipRole>
    </EntityRelationshipRoles>
  </EntityRelationship>
  <EntityRelationship Name="msdyn_bookableresourcecategory_msdyn_actual_ResourceCategory">
    <EntityRelationshipType>OneToMany</EntityRelationshipType>
    <IntroducedVersion>1.0.0.0</IntroducedVersion>
    <IsHierarchical>0</IsHierarchical>
    <ReferencingEntityName>msdyn_actual</ReferencingEntityName>
    <ReferencedEntityName>BookableResourceCategory</ReferencedEntityName>
    <CascadeAssign>NoCascade</CascadeAssign>
    <CascadeDelete>Restrict</CascadeDelete>
    <CascadeReparent>NoCascade</CascadeReparent>
    <CascadeShare>NoCascade</CascadeShare>
    <CascadeUnshare>NoCascade</CascadeUnshare>
    <CascadeRollupView>NoCascade</CascadeRollupView>
    <IsValidForAdvancedFind>1</IsValidForAdvancedFind>
    <ReferencingAttributeName>msdyn_ResourceCategory</ReferencingAttributeName>
    <RelationshipDescription>
      <Descriptions>
        <Description description="Select the role ID of the resource performing the work." languagecode="1033" />
      </Descriptions>
    </RelationshipDescription>
    <EntityRelationshipRoles>
      <EntityRelationshipRole>
        <NavPaneDisplayOption>DoNotDisplay</NavPaneDisplayOption>
        <NavPaneArea>Details</NavPaneArea>
        <NavPaneOrder>10000</NavPaneOrder>
        <NavigationPropertyName>msdyn_ResourceCategory</NavigationPropertyName>
        <CustomLabels>
          <CustomLabel description="" languagecode="1033" />
        </CustomLabels>
        <RelationshipRoleType>1</RelationshipRoleType>
      </EntityRelationshipRole>
      <EntityRelationshipRole>
        <RelationshipRoleType>0</RelationshipRoleType>
      </EntityRelationshipRole>
    </EntityRelationshipRoles>
  </EntityRelationship>
  <EntityRelationship Name="msdyn_bookableresourcecategory_msdyn_estimateline_ResourceCategory">
    <EntityRelationshipType>OneToMany</EntityRelationshipType>
    <IntroducedVersion>1.0.0.0</IntroducedVersion>
    <IsHierarchical>0</IsHierarchical>
    <ReferencingEntityName>msdyn_estimateline</ReferencingEntityName>
    <ReferencedEntityName>BookableResourceCategory</ReferencedEntityName>
    <CascadeAssign>NoCascade</CascadeAssign>
    <CascadeDelete>Restrict</CascadeDelete>
    <CascadeReparent>NoCascade</CascadeReparent>
    <CascadeShare>NoCascade</CascadeShare>
    <CascadeUnshare>NoCascade</CascadeUnshare>
    <CascadeRollupView>NoCascade</CascadeRollupView>
    <IsValidForAdvancedFind>1</IsValidForAdvancedFind>
    <ReferencingAttributeName>msdyn_ResourceCategory</ReferencingAttributeName>
    <RelationshipDescription>
      <Descriptions>
        <Description description="Shows the role of this resource on the estimate line." languagecode="1033" />
      </Descriptions>
    </RelationshipDescription>
    <EntityRelationshipRoles>
      <EntityRelationshipRole>
        <NavPaneDisplayOption>DoNotDisplay</NavPaneDisplayOption>
        <NavPaneArea>Details</NavPaneArea>
        <NavPaneOrder>10000</NavPaneOrder>
        <NavigationPropertyName>msdyn_ResourceCategory</NavigationPropertyName>
        <CustomLabels>
          <CustomLabel description="" languagecode="1033" />
        </CustomLabels>
        <RelationshipRoleType>1</RelationshipRoleType>
      </EntityRelationshipRole>
      <EntityRelationshipRole>
        <RelationshipRoleType>0</RelationshipRoleType>
      </EntityRelationshipRole>
    </EntityRelationshipRoles>
  </EntityRelationship>
  <EntityRelationship Name="msdyn_bookableresourcecategory_msdyn_fact_ResourceCategory">
    <EntityRelationshipType>OneToMany</EntityRelationshipType>
    <IntroducedVersion>1.0.0.1</IntroducedVersion>
    <IsHierarchical>0</IsHierarchical>
    <ReferencingEntityName>msdyn_fact</ReferencingEntityName>
    <ReferencedEntityName>BookableResourceCategory</ReferencedEntityName>
    <CascadeAssign>NoCascade</CascadeAssign>
    <CascadeDelete>Restrict</CascadeDelete>
    <CascadeReparent>NoCascade</CascadeReparent>
    <CascadeShare>NoCascade</CascadeShare>
    <CascadeUnshare>NoCascade</CascadeUnshare>
    <CascadeRollupView>NoCascade</CascadeRollupView>
    <IsValidForAdvancedFind>1</IsValidForAdvancedFind>
    <ReferencingAttributeName>msdyn_ResourceCategory</ReferencingAttributeName>
    <RelationshipDescription>
      <Descriptions>
        <Description description="" languagecode="1033" />
      </Descriptions>
    </RelationshipDescription>
    <EntityRelationshipRoles>
      <EntityRelationshipRole>
        <NavPaneDisplayOption>DoNotDisplay</NavPaneDisplayOption>
        <NavPaneArea>Details</NavPaneArea>
        <NavPaneOrder>10000</NavPaneOrder>
        <NavigationPropertyName>msdyn_ResourceCategory</NavigationPropertyName>
        <CustomLabels>
          <CustomLabel description="" languagecode="1033" />
        </CustomLabels>
        <RelationshipRoleType>1</RelationshipRoleType>
      </EntityRelationshipRole>
      <EntityRelationshipRole>
        <RelationshipRoleType>0</RelationshipRoleType>
      </EntityRelationshipRole>
    </EntityRelationshipRoles>
  </EntityRelationship>
  <EntityRelationship Name="msdyn_bookableresourcecategory_msdyn_invoicelinetransaction_ResourceCategory">
    <EntityRelationshipType>OneToMany</EntityRelationshipType>
    <IntroducedVersion>1.0.0.0</IntroducedVersion>
    <IsHierarchical>0</IsHierarchical>
    <ReferencingEntityName>msdyn_invoicelinetransaction</ReferencingEntityName>
    <ReferencedEntityName>BookableResourceCategory</ReferencedEntityName>
    <CascadeAssign>NoCascade</CascadeAssign>
    <CascadeDelete>Restrict</CascadeDelete>
    <CascadeReparent>NoCascade</CascadeReparent>
    <CascadeShare>NoCascade</CascadeShare>
    <CascadeUnshare>NoCascade</CascadeUnshare>
    <CascadeRollupView>NoCascade</CascadeRollupView>
    <IsValidForAdvancedFind>1</IsValidForAdvancedFind>
    <ReferencingAttributeName>msdyn_ResourceCategory</ReferencingAttributeName>
    <RelationshipDescription>
      <Descriptions>
        <Description description="Select the role that the user resource who logged this transaction worked as." languagecode="1033" />
      </Descriptions>
    </RelationshipDescription>
    <EntityRelationshipRoles>
      <EntityRelationshipRole>
        <NavPaneDisplayOption>DoNotDisplay</NavPaneDisplayOption>
        <NavPaneArea>Details</NavPaneArea>
        <NavPaneOrder>10000</NavPaneOrder>
        <NavigationPropertyName>msdyn_ResourceCategory</NavigationPropertyName>
        <CustomLabels>
          <CustomLabel description="" languagecode="1033" />
        </CustomLabels>
        <RelationshipRoleType>1</RelationshipRoleType>
      </EntityRelationshipRole>
      <EntityRelationshipRole>
        <RelationshipRoleType>0</RelationshipRoleType>
      </EntityRelationshipRole>
    </EntityRelationshipRoles>
  </EntityRelationship>
  <EntityRelationship Name="msdyn_bookableresourcecategory_msdyn_journalline_ResourceCategory">
    <EntityRelationshipType>OneToMany</EntityRelationshipType>
    <IntroducedVersion>1.0.0.0</IntroducedVersion>
    <IsHierarchical>0</IsHierarchical>
    <ReferencingEntityName>msdyn_journalline</ReferencingEntityName>
    <ReferencedEntityName>BookableResourceCategory</ReferencedEntityName>
    <CascadeAssign>NoCascade</CascadeAssign>
    <CascadeDelete>Restrict</CascadeDelete>
    <CascadeReparent>NoCascade</CascadeReparent>
    <CascadeShare>NoCascade</CascadeShare>
    <CascadeUnshare>NoCascade</CascadeUnshare>
    <CascadeRollupView>NoCascade</CascadeRollupView>
    <IsValidForAdvancedFind>1</IsValidForAdvancedFind>
    <ReferencingAttributeName>msdyn_ResourceCategory</ReferencingAttributeName>
    <RelationshipDescription>
      <Descriptions>
        <Description description="Select the resource role." languagecode="1033" />
      </Descriptions>
    </RelationshipDescription>
    <EntityRelationshipRoles>
      <EntityRelationshipRole>
        <NavPaneDisplayOption>DoNotDisplay</NavPaneDisplayOption>
        <NavPaneArea>Details</NavPaneArea>
        <NavPaneOrder>10000</NavPaneOrder>
        <NavigationPropertyName>msdyn_ResourceCategory</NavigationPropertyName>
        <CustomLabels>
          <CustomLabel description="" languagecode="1033" />
        </CustomLabels>
        <RelationshipRoleType>1</RelationshipRoleType>
      </EntityRelationshipRole>
      <EntityRelationshipRole>
        <RelationshipRoleType>0</RelationshipRoleType>
      </EntityRelationshipRole>
    </EntityRelationshipRoles>
  </EntityRelationship>
  <EntityRelationship Name="msdyn_bookableresourcecategory_msdyn_opportunitylineresourcecategory_ResourceCategory">
    <EntityRelationshipType>OneToMany</EntityRelationshipType>
    <IntroducedVersion>1.0.0.1</IntroducedVersion>
    <IsHierarchical>0</IsHierarchical>
    <ReferencingEntityName>msdyn_opportunitylineresourcecategory</ReferencingEntityName>
    <ReferencedEntityName>BookableResourceCategory</ReferencedEntityName>
    <CascadeAssign>NoCascade</CascadeAssign>
    <CascadeDelete>Restrict</CascadeDelete>
    <CascadeReparent>NoCascade</CascadeReparent>
    <CascadeShare>NoCascade</CascadeShare>
    <CascadeUnshare>NoCascade</CascadeUnshare>
    <CascadeRollupView>NoCascade</CascadeRollupView>
    <IsValidForAdvancedFind>1</IsValidForAdvancedFind>
    <ReferencingAttributeName>msdyn_ResourceCategory</ReferencingAttributeName>
    <RelationshipDescription>
      <Descriptions>
        <Description description="Select the role that applies to this opportunity line." languagecode="1033" />
      </Descriptions>
    </RelationshipDescription>
    <EntityRelationshipRoles>
      <EntityRelationshipRole>
        <NavPaneDisplayOption>DoNotDisplay</NavPaneDisplayOption>
        <NavPaneArea>Details</NavPaneArea>
        <NavPaneOrder>10000</NavPaneOrder>
        <NavigationPropertyName>msdyn_ResourceCategory</NavigationPropertyName>
        <CustomLabels>
          <CustomLabel description="" languagecode="1033" />
        </CustomLabels>
        <RelationshipRoleType>1</RelationshipRoleType>
      </EntityRelationshipRole>
      <EntityRelationshipRole>
        <RelationshipRoleType>0</RelationshipRoleType>
      </EntityRelationshipRole>
    </EntityRelationshipRoles>
  </EntityRelationship>
  <EntityRelationship Name="msdyn_bookableresourcecategory_msdyn_opportunitylinetransaction_ResourceCategory">
    <EntityRelationshipType>OneToMany</EntityRelationshipType>
    <IntroducedVersion>1.0.0.1</IntroducedVersion>
    <IsHierarchical>0</IsHierarchical>
    <ReferencingEntityName>msdyn_opportunitylinetransaction</ReferencingEntityName>
    <ReferencedEntityName>BookableResourceCategory</ReferencedEntityName>
    <CascadeAssign>NoCascade</CascadeAssign>
    <CascadeDelete>Restrict</CascadeDelete>
    <CascadeReparent>NoCascade</CascadeReparent>
    <CascadeShare>NoCascade</CascadeShare>
    <CascadeUnshare>NoCascade</CascadeUnshare>
    <CascadeRollupView>NoCascade</CascadeRollupView>
    <IsValidForAdvancedFind>1</IsValidForAdvancedFind>
    <ReferencingAttributeName>msdyn_ResourceCategory</ReferencingAttributeName>
    <RelationshipDescription>
      <Descriptions>
        <Description description="Select the role that is estimated to perform the work." languagecode="1033" />
      </Descriptions>
    </RelationshipDescription>
    <EntityRelationshipRoles>
      <EntityRelationshipRole>
        <NavPaneDisplayOption>DoNotDisplay</NavPaneDisplayOption>
        <NavPaneArea>Details</NavPaneArea>
        <NavPaneOrder>10000</NavPaneOrder>
        <NavigationPropertyName>msdyn_ResourceCategory</NavigationPropertyName>
        <CustomLabels>
          <CustomLabel description="" languagecode="1033" />
        </CustomLabels>
        <RelationshipRoleType>1</RelationshipRoleType>
      </EntityRelationshipRole>
      <EntityRelationshipRole>
        <RelationshipRoleType>0</RelationshipRoleType>
      </EntityRelationshipRole>
    </EntityRelationshipRoles>
  </EntityRelationship>
  <EntityRelationship Name="msdyn_bookableresourcecategory_msdyn_orderlineresourcecategory_ResourceCategory">
    <EntityRelationshipType>OneToMany</EntityRelationshipType>
    <IntroducedVersion>1.0.0.1</IntroducedVersion>
    <IsHierarchical>0</IsHierarchical>
    <ReferencingEntityName>msdyn_orderlineresourcecategory</ReferencingEntityName>
    <ReferencedEntityName>BookableResourceCategory</ReferencedEntityName>
    <CascadeAssign>NoCascade</CascadeAssign>
    <CascadeDelete>Restrict</CascadeDelete>
    <CascadeReparent>NoCascade</CascadeReparent>
    <CascadeShare>NoCascade</CascadeShare>
    <CascadeUnshare>NoCascade</CascadeUnshare>
    <CascadeRollupView>NoCascade</CascadeRollupView>
    <IsValidForAdvancedFind>1</IsValidForAdvancedFind>
    <ReferencingAttributeName>msdyn_ResourceCategory</ReferencingAttributeName>
    <RelationshipDescription>
      <Descriptions>
        <Description description="Select the role that is being associated to the project contract line." languagecode="1033" />
      </Descriptions>
    </RelationshipDescription>
    <EntityRelationshipRoles>
      <EntityRelationshipRole>
        <NavPaneDisplayOption>DoNotDisplay</NavPaneDisplayOption>
        <NavPaneArea>Details</NavPaneArea>
        <NavPaneOrder>10000</NavPaneOrder>
        <NavigationPropertyName>msdyn_ResourceCategory</NavigationPropertyName>
        <CustomLabels>
          <CustomLabel description="" languagecode="1033" />
        </CustomLabels>
        <RelationshipRoleType>1</RelationshipRoleType>
      </EntityRelationshipRole>
      <EntityRelationshipRole>
        <RelationshipRoleType>0</RelationshipRoleType>
      </EntityRelationshipRole>
    </EntityRelationshipRoles>
  </EntityRelationship>
  <EntityRelationship Name="msdyn_bookableresourcecategory_msdyn_orderlinetransaction_ResourceCategory">
    <EntityRelationshipType>OneToMany</EntityRelationshipType>
    <IntroducedVersion>1.0.0.0</IntroducedVersion>
    <IsHierarchical>0</IsHierarchical>
    <ReferencingEntityName>msdyn_orderlinetransaction</ReferencingEntityName>
    <ReferencedEntityName>BookableResourceCategory</ReferencedEntityName>
    <CascadeAssign>NoCascade</CascadeAssign>
    <CascadeDelete>Restrict</CascadeDelete>
    <CascadeReparent>NoCascade</CascadeReparent>
    <CascadeShare>NoCascade</CascadeShare>
    <CascadeUnshare>NoCascade</CascadeUnshare>
    <CascadeRollupView>NoCascade</CascadeRollupView>
    <IsValidForAdvancedFind>1</IsValidForAdvancedFind>
    <ReferencingAttributeName>msdyn_ResourceCategory</ReferencingAttributeName>
    <RelationshipDescription>
      <Descriptions>
        <Description description="Select the name of the role that is estimated to perform this work." languagecode="1033" />
      </Descriptions>
    </RelationshipDescription>
    <EntityRelationshipRoles>
      <EntityRelationshipRole>
        <NavPaneDisplayOption>DoNotDisplay</NavPaneDisplayOption>
        <NavPaneArea>Details</NavPaneArea>
        <NavPaneOrder>10000</NavPaneOrder>
        <NavigationPropertyName>msdyn_ResourceCategory</NavigationPropertyName>
        <CustomLabels>
          <CustomLabel description="" languagecode="1033" />
        </CustomLabels>
        <RelationshipRoleType>1</RelationshipRoleType>
      </EntityRelationshipRole>
      <EntityRelationshipRole>
        <RelationshipRoleType>0</RelationshipRoleType>
      </EntityRelationshipRole>
    </EntityRelationshipRoles>
  </EntityRelationship>
  <EntityRelationship Name="msdyn_bookableresourcecategory_msdyn_projectapproval_ResourceCategory">
    <EntityRelationshipType>OneToMany</EntityRelationshipType>
    <IntroducedVersion>1.0.0.1</IntroducedVersion>
    <IsHierarchical>0</IsHierarchical>
    <ReferencingEntityName>msdyn_projectapproval</ReferencingEntityName>
    <ReferencedEntityName>BookableResourceCategory</ReferencedEntityName>
    <CascadeAssign>NoCascade</CascadeAssign>
    <CascadeDelete>RemoveLink</CascadeDelete>
    <CascadeReparent>NoCascade</CascadeReparent>
    <CascadeShare>NoCascade</CascadeShare>
    <CascadeUnshare>NoCascade</CascadeUnshare>
    <CascadeRollupView>NoCascade</CascadeRollupView>
    <IsValidForAdvancedFind>1</IsValidForAdvancedFind>
    <ReferencingAttributeName>msdyn_ResourceCategory</ReferencingAttributeName>
    <RelationshipDescription>
      <Descriptions>
        <Description description="Shows the role for the resource for this transaction." languagecode="1033" />
      </Descriptions>
    </RelationshipDescription>
    <EntityRelationshipRoles>
      <EntityRelationshipRole>
        <NavPaneDisplayOption>UseCollectionName</NavPaneDisplayOption>
        <NavPaneArea>Details</NavPaneArea>
        <NavPaneOrder>10000</NavPaneOrder>
        <NavigationPropertyName>msdyn_ResourceCategory</NavigationPropertyName>
        <CustomLabels>
          <CustomLabel description="" languagecode="1033" />
        </CustomLabels>
        <RelationshipRoleType>1</RelationshipRoleType>
      </EntityRelationshipRole>
      <EntityRelationshipRole>
        <RelationshipRoleType>0</RelationshipRoleType>
      </EntityRelationshipRole>
    </EntityRelationshipRoles>
  </EntityRelationship>
  <EntityRelationship Name="msdyn_bookableresourcecategory_msdyn_projectparameter_projectmanagerrole">
    <EntityRelationshipType>OneToMany</EntityRelationshipType>
    <IntroducedVersion>1.0.1.1</IntroducedVersion>
    <IsHierarchical>0</IsHierarchical>
    <ReferencingEntityName>msdyn_projectparameter</ReferencingEntityName>
    <ReferencedEntityName>BookableResourceCategory</ReferencedEntityName>
    <CascadeAssign>NoCascade</CascadeAssign>
    <CascadeDelete>Restrict</CascadeDelete>
    <CascadeReparent>NoCascade</CascadeReparent>
    <CascadeShare>NoCascade</CascadeShare>
    <CascadeUnshare>NoCascade</CascadeUnshare>
    <CascadeRollupView>NoCascade</CascadeRollupView>
    <IsValidForAdvancedFind>1</IsValidForAdvancedFind>
    <ReferencingAttributeName>msdyn_projectmanagerrole</ReferencingAttributeName>
    <RelationshipDescription>
      <Descriptions>
        <Description description="Shows the default role to be used when a project manager is added to the project team." languagecode="1033" />
      </Descriptions>
    </RelationshipDescription>
    <EntityRelationshipRoles>
      <EntityRelationshipRole>
        <NavPaneDisplayOption>UseCollectionName</NavPaneDisplayOption>
        <NavPaneArea>Details</NavPaneArea>
        <NavPaneOrder>10000</NavPaneOrder>
        <NavigationPropertyName>msdyn_projectmanagerrole</NavigationPropertyName>
        <CustomLabels>
          <CustomLabel description="" languagecode="1033" />
        </CustomLabels>
        <RelationshipRoleType>1</RelationshipRoleType>
      </EntityRelationshipRole>
      <EntityRelationshipRole>
        <RelationshipRoleType>0</RelationshipRoleType>
      </EntityRelationshipRole>
    </EntityRelationshipRoles>
  </EntityRelationship>
  <EntityRelationship Name="msdyn_bookableresourcecategory_msdyn_projectparameter_teammemberrole">
    <EntityRelationshipType>OneToMany</EntityRelationshipType>
    <IntroducedVersion>1.0.1.1</IntroducedVersion>
    <IsHierarchical>0</IsHierarchical>
    <ReferencingEntityName>msdyn_projectparameter</ReferencingEntityName>
    <ReferencedEntityName>BookableResourceCategory</ReferencedEntityName>
    <CascadeAssign>NoCascade</CascadeAssign>
    <CascadeDelete>Restrict</CascadeDelete>
    <CascadeReparent>NoCascade</CascadeReparent>
    <CascadeShare>NoCascade</CascadeShare>
    <CascadeUnshare>NoCascade</CascadeUnshare>
    <CascadeRollupView>NoCascade</CascadeRollupView>
    <IsValidForAdvancedFind>1</IsValidForAdvancedFind>
    <ReferencingAttributeName>msdyn_teammemberrole</ReferencingAttributeName>
    <RelationshipDescription>
      <Descriptions>
        <Description description="Shows the default role to be used when a team member is added to the project team." languagecode="1033" />
      </Descriptions>
    </RelationshipDescription>
    <EntityRelationshipRoles>
      <EntityRelationshipRole>
        <NavPaneDisplayOption>UseCollectionName</NavPaneDisplayOption>
        <NavPaneArea>Details</NavPaneArea>
        <NavPaneOrder>10000</NavPaneOrder>
        <NavigationPropertyName>msdyn_teammemberrole</NavigationPropertyName>
        <CustomLabels>
          <CustomLabel description="" languagecode="1033" />
        </CustomLabels>
        <RelationshipRoleType>1</RelationshipRoleType>
      </EntityRelationshipRole>
      <EntityRelationshipRole>
        <RelationshipRoleType>0</RelationshipRoleType>
      </EntityRelationshipRole>
    </EntityRelationshipRoles>
  </EntityRelationship>
  <EntityRelationship Name="msdyn_bookableresourcecategory_msdyn_projecttask_resourcecategory">
    <EntityRelationshipType>OneToMany</EntityRelationshipType>
    <IntroducedVersion>1.0.0.1</IntroducedVersion>
    <IsHierarchical>0</IsHierarchical>
    <ReferencingEntityName>msdyn_projecttask</ReferencingEntityName>
    <ReferencedEntityName>BookableResourceCategory</ReferencedEntityName>
    <CascadeAssign>NoCascade</CascadeAssign>
    <CascadeDelete>Restrict</CascadeDelete>
    <CascadeReparent>NoCascade</CascadeReparent>
    <CascadeShare>NoCascade</CascadeShare>
    <CascadeUnshare>NoCascade</CascadeUnshare>
    <CascadeRollupView>NoCascade</CascadeRollupView>
    <IsValidForAdvancedFind>1</IsValidForAdvancedFind>
    <ReferencingAttributeName>msdyn_resourcecategory</ReferencingAttributeName>
    <RelationshipDescription>
      <Descriptions>
        <Description description="Select the resource role for the task." languagecode="1033" />
      </Descriptions>
    </RelationshipDescription>
    <EntityRelationshipRoles>
      <EntityRelationshipRole>
        <NavPaneDisplayOption>DoNotDisplay</NavPaneDisplayOption>
        <NavPaneArea>Details</NavPaneArea>
        <NavPaneOrder>10000</NavPaneOrder>
        <NavigationPropertyName>msdyn_resourcecategory</NavigationPropertyName>
        <CustomLabels>
          <CustomLabel description="" languagecode="1033" />
        </CustomLabels>
        <RelationshipRoleType>1</RelationshipRoleType>
      </EntityRelationshipRole>
      <EntityRelationshipRole>
        <RelationshipRoleType>0</RelationshipRoleType>
      </EntityRelationshipRole>
    </EntityRelationshipRoles>
  </EntityRelationship>
  <EntityRelationship Name="msdyn_bookableresourcecategory_msdyn_projectteam_resourcecategory">
    <EntityRelationshipType>OneToMany</EntityRelationshipType>
    <IntroducedVersion>1.0.0.0</IntroducedVersion>
    <IsHierarchical>0</IsHierarchical>
    <ReferencingEntityName>msdyn_projectteam</ReferencingEntityName>
    <ReferencedEntityName>BookableResourceCategory</ReferencedEntityName>
    <CascadeAssign>NoCascade</CascadeAssign>
    <CascadeDelete>Restrict</CascadeDelete>
    <CascadeReparent>NoCascade</CascadeReparent>
    <CascadeShare>NoCascade</CascadeShare>
    <CascadeUnshare>NoCascade</CascadeUnshare>
    <CascadeRollupView>NoCascade</CascadeRollupView>
    <IsValidForAdvancedFind>1</IsValidForAdvancedFind>
    <ReferencingAttributeName>msdyn_resourcecategory</ReferencingAttributeName>
    <RelationshipDescription>
      <Descriptions>
        <Description description="Select the role this team member is playing in this team." languagecode="1033" />
      </Descriptions>
    </RelationshipDescription>
    <EntityRelationshipRoles>
      <EntityRelationshipRole>
        <NavPaneDisplayOption>DoNotDisplay</NavPaneDisplayOption>
        <NavPaneArea>Details</NavPaneArea>
        <NavPaneOrder>10000</NavPaneOrder>
        <NavigationPropertyName>msdyn_resourcecategory</NavigationPropertyName>
        <CustomLabels>
          <CustomLabel description="" languagecode="1033" />
        </CustomLabels>
        <RelationshipRoleType>1</RelationshipRoleType>
      </EntityRelationshipRole>
      <EntityRelationshipRole>
        <RelationshipRoleType>0</RelationshipRoleType>
      </EntityRelationshipRole>
    </EntityRelationshipRoles>
  </EntityRelationship>
  <EntityRelationship Name="msdyn_bookableresourcecategory_msdyn_quotelineanalyticsbreakdown_ResourceCategory">
    <EntityRelationshipType>OneToMany</EntityRelationshipType>
    <IntroducedVersion>1.0.0.1</IntroducedVersion>
    <IsHierarchical>0</IsHierarchical>
    <ReferencingEntityName>msdyn_quotelineanalyticsbreakdown</ReferencingEntityName>
    <ReferencedEntityName>BookableResourceCategory</ReferencedEntityName>
    <CascadeAssign>NoCascade</CascadeAssign>
    <CascadeDelete>RemoveLink</CascadeDelete>
    <CascadeReparent>NoCascade</CascadeReparent>
    <CascadeShare>NoCascade</CascadeShare>
    <CascadeUnshare>NoCascade</CascadeUnshare>
    <CascadeRollupView>NoCascade</CascadeRollupView>
    <IsValidForAdvancedFind>1</IsValidForAdvancedFind>
    <ReferencingAttributeName>msdyn_ResourceCategory</ReferencingAttributeName>
    <RelationshipDescription>
      <Descriptions>
        <Description description="Select the role that is estimated on the quote line." languagecode="1033" />
      </Descriptions>
    </RelationshipDescription>
    <EntityRelationshipRoles>
      <EntityRelationshipRole>
        <NavPaneDisplayOption>UseCollectionName</NavPaneDisplayOption>
        <NavPaneArea>Details</NavPaneArea>
        <NavPaneOrder>10000</NavPaneOrder>
        <NavigationPropertyName>msdyn_ResourceCategory</NavigationPropertyName>
        <CustomLabels>
          <CustomLabel description="" languagecode="1033" />
        </CustomLabels>
        <RelationshipRoleType>1</RelationshipRoleType>
      </EntityRelationshipRole>
      <EntityRelationshipRole>
        <RelationshipRoleType>0</RelationshipRoleType>
      </EntityRelationshipRole>
    </EntityRelationshipRoles>
  </EntityRelationship>
  <EntityRelationship Name="msdyn_bookableresourcecategory_msdyn_quotelineresourcecategory_ResourceCategory">
    <EntityRelationshipType>OneToMany</EntityRelationshipType>
    <IntroducedVersion>1.0.0.1</IntroducedVersion>
    <IsHierarchical>0</IsHierarchical>
    <ReferencingEntityName>msdyn_quotelineresourcecategory</ReferencingEntityName>
    <ReferencedEntityName>BookableResourceCategory</ReferencedEntityName>
    <CascadeAssign>NoCascade</CascadeAssign>
    <CascadeDelete>Restrict</CascadeDelete>
    <CascadeReparent>NoCascade</CascadeReparent>
    <CascadeShare>NoCascade</CascadeShare>
    <CascadeUnshare>NoCascade</CascadeUnshare>
    <CascadeRollupView>NoCascade</CascadeRollupView>
    <IsValidForAdvancedFind>1</IsValidForAdvancedFind>
    <ReferencingAttributeName>msdyn_ResourceCategory</ReferencingAttributeName>
    <RelationshipDescription>
      <Descriptions>
        <Description description="Select the role that is being quoted on this quote line." languagecode="1033" />
      </Descriptions>
    </RelationshipDescription>
    <EntityRelationshipRoles>
      <EntityRelationshipRole>
        <NavPaneDisplayOption>DoNotDisplay</NavPaneDisplayOption>
        <NavPaneArea>Details</NavPaneArea>
        <NavPaneOrder>10000</NavPaneOrder>
        <NavigationPropertyName>msdyn_ResourceCategory</NavigationPropertyName>
        <CustomLabels>
          <CustomLabel description="" languagecode="1033" />
        </CustomLabels>
        <RelationshipRoleType>1</RelationshipRoleType>
      </EntityRelationshipRole>
      <EntityRelationshipRole>
        <RelationshipRoleType>0</RelationshipRoleType>
      </EntityRelationshipRole>
    </EntityRelationshipRoles>
  </EntityRelationship>
  <EntityRelationship Name="msdyn_bookableresourcecategory_msdyn_quotelinetransaction_ResourceCategory">
    <EntityRelationshipType>OneToMany</EntityRelationshipType>
    <IntroducedVersion>1.0.0.1</IntroducedVersion>
    <IsHierarchical>0</IsHierarchical>
    <ReferencingEntityName>msdyn_quotelinetransaction</ReferencingEntityName>
    <ReferencedEntityName>BookableResourceCategory</ReferencedEntityName>
    <CascadeAssign>NoCascade</CascadeAssign>
    <CascadeDelete>Restrict</CascadeDelete>
    <CascadeReparent>NoCascade</CascadeReparent>
    <CascadeShare>NoCascade</CascadeShare>
    <CascadeUnshare>NoCascade</CascadeUnshare>
    <CascadeRollupView>NoCascade</CascadeRollupView>
    <IsValidForAdvancedFind>1</IsValidForAdvancedFind>
    <ReferencingAttributeName>msdyn_ResourceCategory</ReferencingAttributeName>
    <RelationshipDescription>
      <Descriptions>
        <Description description="Select the role on the quote line estimate." languagecode="1033" />
      </Descriptions>
    </RelationshipDescription>
    <EntityRelationshipRoles>
      <EntityRelationshipRole>
        <NavPaneDisplayOption>DoNotDisplay</NavPaneDisplayOption>
        <NavPaneArea>Details</NavPaneArea>
        <NavPaneOrder>10000</NavPaneOrder>
        <NavigationPropertyName>msdyn_ResourceCategory</NavigationPropertyName>
        <CustomLabels>
          <CustomLabel description="" languagecode="1033" />
        </CustomLabels>
        <RelationshipRoleType>1</RelationshipRoleType>
      </EntityRelationshipRole>
      <EntityRelationshipRole>
        <RelationshipRoleType>0</RelationshipRoleType>
      </EntityRelationshipRole>
    </EntityRelationshipRoles>
  </EntityRelationship>
  <EntityRelationship Name="msdyn_bookableresourcecategory_msdyn_resourcecategorymarkuppricelevel_resourcecategory">
    <EntityRelationshipType>OneToMany</EntityRelationshipType>
    <IntroducedVersion>2.2.0.0</IntroducedVersion>
    <IsHierarchical>0</IsHierarchical>
    <ReferencingEntityName>msdyn_resourcecategorymarkuppricelevel</ReferencingEntityName>
    <ReferencedEntityName>BookableResourceCategory</ReferencedEntityName>
    <CascadeAssign>NoCascade</CascadeAssign>
    <CascadeDelete>Restrict</CascadeDelete>
    <CascadeReparent>NoCascade</CascadeReparent>
    <CascadeShare>NoCascade</CascadeShare>
    <CascadeUnshare>NoCascade</CascadeUnshare>
    <CascadeRollupView>NoCascade</CascadeRollupView>
    <IsValidForAdvancedFind>1</IsValidForAdvancedFind>
    <ReferencingAttributeName>msdyn_resourcecategory</ReferencingAttributeName>
    <RelationshipDescription>
      <Descriptions>
        <Description description="Select the role that the price is being set for." languagecode="1033" />
      </Descriptions>
    </RelationshipDescription>
    <EntityRelationshipRoles>
      <EntityRelationshipRole>
        <NavPaneDisplayOption>UseCollectionName</NavPaneDisplayOption>
        <NavPaneArea>Details</NavPaneArea>
        <NavPaneOrder>10000</NavPaneOrder>
        <NavigationPropertyName>msdyn_resourcecategory</NavigationPropertyName>
        <CustomLabels>
          <CustomLabel description="" languagecode="1033" />
        </CustomLabels>
        <RelationshipRoleType>1</RelationshipRoleType>
      </EntityRelationshipRole>
      <EntityRelationshipRole>
        <RelationshipRoleType>0</RelationshipRoleType>
      </EntityRelationshipRole>
    </EntityRelationshipRoles>
  </EntityRelationship>
  <EntityRelationship Name="msdyn_bookableresourcecategory_msdyn_resourcecategorypricelevel_ResourceCategory">
    <EntityRelationshipType>OneToMany</EntityRelationshipType>
    <IntroducedVersion>1.0.0.0</IntroducedVersion>
    <IsHierarchical>0</IsHierarchical>
    <ReferencingEntityName>msdyn_resourcecategorypricelevel</ReferencingEntityName>
    <ReferencedEntityName>BookableResourceCategory</ReferencedEntityName>
    <CascadeAssign>NoCascade</CascadeAssign>
    <CascadeDelete>Restrict</CascadeDelete>
    <CascadeReparent>NoCascade</CascadeReparent>
    <CascadeShare>NoCascade</CascadeShare>
    <CascadeUnshare>NoCascade</CascadeUnshare>
    <CascadeRollupView>NoCascade</CascadeRollupView>
    <IsValidForAdvancedFind>1</IsValidForAdvancedFind>
    <ReferencingAttributeName>msdyn_ResourceCategory</ReferencingAttributeName>
    <RelationshipDescription>
      <Descriptions>
        <Description description="Select the role that the price is being set for." languagecode="1033" />
      </Descriptions>
    </RelationshipDescription>
    <EntityRelationshipRoles>
      <EntityRelationshipRole>
        <NavPaneDisplayOption>DoNotDisplay</NavPaneDisplayOption>
        <NavPaneArea>Details</NavPaneArea>
        <NavPaneOrder>10000</NavPaneOrder>
        <NavigationPropertyName>msdyn_ResourceCategory</NavigationPropertyName>
        <CustomLabels>
          <CustomLabel description="" languagecode="1033" />
        </CustomLabels>
        <RelationshipRoleType>1</RelationshipRoleType>
      </EntityRelationshipRole>
      <EntityRelationshipRole>
        <RelationshipRoleType>0</RelationshipRoleType>
      </EntityRelationshipRole>
    </EntityRelationshipRoles>
  </EntityRelationship>
  <EntityRelationship Name="msdyn_bookableresourcecategory_msdyn_resourcerequest_roleid">
    <EntityRelationshipType>OneToMany</EntityRelationshipType>
    <IntroducedVersion>1.0.0.0</IntroducedVersion>
    <IsHierarchical>0</IsHierarchical>
    <ReferencingEntityName>msdyn_resourcerequest</ReferencingEntityName>
    <ReferencedEntityName>BookableResourceCategory</ReferencedEntityName>
    <CascadeAssign>NoCascade</CascadeAssign>
    <CascadeDelete>RemoveLink</CascadeDelete>
    <CascadeReparent>NoCascade</CascadeReparent>
    <CascadeShare>NoCascade</CascadeShare>
    <CascadeUnshare>NoCascade</CascadeUnshare>
    <CascadeRollupView>NoCascade</CascadeRollupView>
    <IsValidForAdvancedFind>1</IsValidForAdvancedFind>
    <ReferencingAttributeName>msdyn_roleid</ReferencingAttributeName>
    <RelationshipDescription>
      <Descriptions>
        <Description description="Primary role id in resource requirement" languagecode="1033" />
      </Descriptions>
    </RelationshipDescription>
    <EntityRelationshipRoles>
      <EntityRelationshipRole>
        <NavPaneDisplayOption>UseCollectionName</NavPaneDisplayOption>
        <NavPaneArea>Details</NavPaneArea>
        <NavPaneOrder>10000</NavPaneOrder>
        <NavigationPropertyName>msdyn_roleid</NavigationPropertyName>
        <CustomLabels>
          <CustomLabel description="" languagecode="1033" />
        </CustomLabels>
        <RelationshipRoleType>1</RelationshipRoleType>
      </EntityRelationshipRole>
      <EntityRelationshipRole>
        <RelationshipRoleType>0</RelationshipRoleType>
      </EntityRelationshipRole>
    </EntityRelationshipRoles>
  </EntityRelationship>
  <EntityRelationship Name="msdyn_bookableresourcecategory_msdyn_rolecompetencyrequirement_resourcecategory">
    <EntityRelationshipType>OneToMany</EntityRelationshipType>
    <IntroducedVersion>1.0.0.0</IntroducedVersion>
    <IsHierarchical>0</IsHierarchical>
    <ReferencingEntityName>msdyn_rolecompetencyrequirement</ReferencingEntityName>
    <ReferencedEntityName>BookableResourceCategory</ReferencedEntityName>
    <CascadeAssign>Cascade</CascadeAssign>
    <CascadeDelete>Cascade</CascadeDelete>
    <CascadeReparent>Cascade</CascadeReparent>
    <CascadeShare>Cascade</CascadeShare>
    <CascadeUnshare>Cascade</CascadeUnshare>
    <CascadeRollupView>NoCascade</CascadeRollupView>
    <IsValidForAdvancedFind>1</IsValidForAdvancedFind>
    <ReferencingAttributeName>msdyn_resourcecategory</ReferencingAttributeName>
    <RelationshipDescription>
      <Descriptions>
        <Description description="Select the resource role." languagecode="1033" />
      </Descriptions>
    </RelationshipDescription>
    <EntityRelationshipRoles>
      <EntityRelationshipRole>
        <NavPaneDisplayOption>DoNotDisplay</NavPaneDisplayOption>
        <NavPaneArea>Details</NavPaneArea>
        <NavPaneOrder>10000</NavPaneOrder>
        <NavigationPropertyName>msdyn_resourcecategory</NavigationPropertyName>
        <CustomLabels>
          <CustomLabel description="" languagecode="1033" />
        </CustomLabels>
        <RelationshipRoleType>1</RelationshipRoleType>
      </EntityRelationshipRole>
      <EntityRelationshipRole>
        <RelationshipRoleType>0</RelationshipRoleType>
      </EntityRelationshipRole>
    </EntityRelationshipRoles>
  </EntityRelationship>
  <EntityRelationship Name="msdyn_bookableresourcecategory_msdyn_roleutilization_role">
    <EntityRelationshipType>OneToMany</EntityRelationshipType>
    <IntroducedVersion>1.0.0.1</IntroducedVersion>
    <IsHierarchical>0</IsHierarchical>
    <ReferencingEntityName>msdyn_roleutilization</ReferencingEntityName>
    <ReferencedEntityName>BookableResourceCategory</ReferencedEntityName>
    <CascadeAssign>NoCascade</CascadeAssign>
    <CascadeDelete>RemoveLink</CascadeDelete>
    <CascadeReparent>NoCascade</CascadeReparent>
    <CascadeShare>NoCascade</CascadeShare>
    <CascadeUnshare>NoCascade</CascadeUnshare>
    <CascadeRollupView>NoCascade</CascadeRollupView>
    <IsValidForAdvancedFind>1</IsValidForAdvancedFind>
    <ReferencingAttributeName>msdyn_role</ReferencingAttributeName>
    <RelationshipDescription>
      <Descriptions>
        <Description description="Resource role" languagecode="1033" />
      </Descriptions>
    </RelationshipDescription>
    <EntityRelationshipRoles>
      <EntityRelationshipRole>
        <NavPaneDisplayOption>UseCollectionName</NavPaneDisplayOption>
        <NavPaneArea>Details</NavPaneArea>
        <NavPaneOrder>10000</NavPaneOrder>
        <NavigationPropertyName>msdyn_role</NavigationPropertyName>
        <CustomLabels>
          <CustomLabel description="" languagecode="1033" />
        </CustomLabels>
        <RelationshipRoleType>1</RelationshipRoleType>
      </EntityRelationshipRole>
      <EntityRelationshipRole>
        <RelationshipRoleType>0</RelationshipRoleType>
      </EntityRelationshipRole>
    </EntityRelationshipRoles>
  </EntityRelationship>
  <EntityRelationship Name="msdyn_bookableresourcecategory_msdyn_timeentry_resourceCategory">
    <EntityRelationshipType>OneToMany</EntityRelationshipType>
    <IntroducedVersion>1.0.0.0</IntroducedVersion>
    <IsHierarchical>0</IsHierarchical>
    <ReferencingEntityName>msdyn_timeentry</ReferencingEntityName>
    <ReferencedEntityName>BookableResourceCategory</ReferencedEntityName>
    <CascadeAssign>NoCascade</CascadeAssign>
    <CascadeDelete>Restrict</CascadeDelete>
    <CascadeReparent>NoCascade</CascadeReparent>
    <CascadeShare>NoCascade</CascadeShare>
    <CascadeUnshare>NoCascade</CascadeUnshare>
    <CascadeRollupView>NoCascade</CascadeRollupView>
    <IsValidForAdvancedFind>1</IsValidForAdvancedFind>
    <ReferencingAttributeName>msdyn_resourceCategory</ReferencingAttributeName>
    <RelationshipDescription>
      <Descriptions>
        <Description description="Select the role that the user has in the project that the time entry is for." languagecode="1033" />
      </Descriptions>
    </RelationshipDescription>
    <EntityRelationshipRoles>
      <EntityRelationshipRole>
        <NavPaneDisplayOption>DoNotDisplay</NavPaneDisplayOption>
        <NavPaneArea>Details</NavPaneArea>
        <NavPaneOrder>10000</NavPaneOrder>
        <NavigationPropertyName>msdyn_resourceCategory</NavigationPropertyName>
        <CustomLabels>
          <CustomLabel description="" languagecode="1033" />
        </CustomLabels>
        <RelationshipRoleType>1</RelationshipRoleType>
      </EntityRelationshipRole>
      <EntityRelationshipRole>
        <RelationshipRoleType>0</RelationshipRoleType>
      </EntityRelationshipRole>
    </EntityRelationshipRoles>
  </EntityRelationship>
  <EntityRelationship Name="msdyn_bookableresourcecategory_requirementresourcecategory_ResourceCategory">
    <EntityRelationshipType>OneToMany</EntityRelationshipType>
    <IntroducedVersion>1.0.0.5</IntroducedVersion>
    <IsHierarchical>0</IsHierarchical>
    <ReferencingEntityName>msdyn_requirementresourcecategory</ReferencingEntityName>
    <ReferencedEntityName>BookableResourceCategory</ReferencedEntityName>
    <CascadeAssign>NoCascade</CascadeAssign>
    <CascadeDelete>RemoveLink</CascadeDelete>
    <CascadeReparent>NoCascade</CascadeReparent>
    <CascadeShare>NoCascade</CascadeShare>
    <CascadeUnshare>NoCascade</CascadeUnshare>
    <CascadeRollupView>NoCascade</CascadeRollupView>
    <IsValidForAdvancedFind>1</IsValidForAdvancedFind>
    <ReferencingAttributeName>msdyn_ResourceCategory</ReferencingAttributeName>
    <RelationshipDescription>
      <Descriptions>
        <Description description="Resource Category" languagecode="1033" />
      </Descriptions>
    </RelationshipDescription>
    <EntityRelationshipRoles>
      <EntityRelationshipRole>
        <NavPaneDisplayOption>UseCollectionName</NavPaneDisplayOption>
        <NavPaneArea>Details</NavPaneArea>
        <NavPaneOrder>10000</NavPaneOrder>
        <NavigationPropertyName>msdyn_ResourceCategory</NavigationPropertyName>
        <CustomLabels>
          <CustomLabel description="" languagecode="1033" />
        </CustomLabels>
        <RelationshipRoleType>1</RelationshipRoleType>
      </EntityRelationshipRole>
      <EntityRelationshipRole>
        <RelationshipRoleType>0</RelationshipRoleType>
      </EntityRelationshipRole>
    </EntityRelationshipRoles>
  </EntityRelationship>
  <EntityRelationship Name="msdyn_bookableresourcecategory_resourcerequirement">
    <EntityRelationshipType>OneToMany</EntityRelationshipType>
    <IntroducedVersion>1.0</IntroducedVersion>
    <IsHierarchical>0</IsHierarchical>
    <ReferencingEntityName>msdyn_resourcerequirement</ReferencingEntityName>
    <ReferencedEntityName>BookableResourceCategory</ReferencedEntityName>
    <CascadeAssign>NoCascade</CascadeAssign>
    <CascadeDelete>RemoveLink</CascadeDelete>
    <CascadeReparent>NoCascade</CascadeReparent>
    <CascadeShare>NoCascade</CascadeShare>
    <CascadeUnshare>NoCascade</CascadeUnshare>
    <CascadeRollupView>NoCascade</CascadeRollupView>
    <IsValidForAdvancedFind>1</IsValidForAdvancedFind>
    <ReferencingAttributeName>msdyn_roleid</ReferencingAttributeName>
    <RelationshipDescription>
      <Descriptions>
        <Description description="Select the required role." languagecode="1033" />
      </Descriptions>
    </RelationshipDescription>
    <EntityRelationshipRoles>
      <EntityRelationshipRole>
        <NavPaneDisplayOption>UseCollectionName</NavPaneDisplayOption>
        <NavPaneArea>Details</NavPaneArea>
        <NavPaneOrder>10000</NavPaneOrder>
        <NavigationPropertyName>msdyn_roleid</NavigationPropertyName>
        <CustomLabels>
          <CustomLabel description="" languagecode="1033" />
        </CustomLabels>
        <RelationshipRoleType>1</RelationshipRoleType>
      </EntityRelationshipRole>
      <EntityRelationshipRole>
        <RelationshipRoleType>0</RelationshipRoleType>
      </EntityRelationshipRole>
    </EntityRelationshipRoles>
  </EntityRelationship>
</EntityRelationships>